{"ุจุงูุง": ["ูุฑุฏุง ูู ุจุงูุง ุบุฐุง ุฏุงุฑู ฺฉุณ ุงุณุชูุงุฏู ูฺฉููุ", "ูู ุจุงูุง ุฏุงุฑู ฺฉุณ ูุฎูุงุฏุ", "ุณูโุดูุจู  ูู ุจุงูุง ุฏุงุฑู", "ฺูุงุฑุดูุจู ูู ุจุงูุง ูุงูุงุฑ ุฏุงุฑูุฺฉุจุงุจ\nูุงฺฏุฐุงุฑ ุดุฏ", "ูู 2 ุฏุงุฑู", "ุขุจฺฏูุดุช ูู ุจุงูุง ุฏุงุฑู\nุงุณุชูุงุฏู", "ูู ุจุงูุง ุฏุงุฑู\n\nุงุณุชูุงุฏู ุดุฏ", "ูู ุจุงูุง ุฏุงุฑู.", "ูู ุจุงูุง ฺฉุฏ ุฏุงุฑู", "ูู ุจุงูุง ฺฉูุจุฏู ุฏุงุฑู", "ูู ุจุงูุง ุฏุงุฑู ุงฺฏู ูููุฒ ูุณุช", "ูู ุจุงูุง ุฏุงุฑู\n-ุงุณุชูุงุฏู ุดุฏ-", "ูู ุจุงูุง ุบุฐุง ุฏุงุฑู \nุงุณุชูุงุฏู ุดุฏ", "ูุฑุฏุง ูุงูุงุฑ ูู ุงูุฑุงุจุงุฏ ุฏุงุฑู", "ูู ุจุงูุง ฺฉุดฺฉ ุจุงุฏูุฌุงู ุฏุงุฑู\nุงุณุชูุงุฏู ุดุฏ", "ุณูุงู ูู ุจุงูุง ุบุฐุง ุฏุงุฑู", "ุจฺู ูุง ุงุญุงูุง ฺฉุณ ุงูุงู ุณูู ุงูุฑุขุจุงุฏ ูุณุชุด ฺฉู ุตุฑูุง ฺฉุฏ ููู ุงุณุชูุงุฏู ฺฉููุ\n\nุงุญุชูุงู ุฏุงุฑู ุฌุฑูู ุจุดู๐", "ูู ุจุงูุง ุฏุงุฑู ุงุณุชูุงุฏู ุดุฏ", "ูุงูุงุฑ ูุฑุฏุง ูู ุจุงูุง ุฏุงุฑู\nุงุณุชูุงุฏู ุดุฏ", "ูู ุจุงูุง ุฒุฑุดฺฉ ูพูู ุจุง ูุฑุบ ุฏุงุฑู\n(ุงุณุชูุงุฏู ุดุฏ)", "ูู ุจุงูุง ุฏุงุฑู\nูู ุงูุขู ุจฺฏุฑู\n\nุดุฏ", "ูุงูุงุฑ ูู ุจุงูุง\n#ุงูุฏุง"], "ูพุงู": ["ูู ูพุงู ุฏุงุฑู\nููุฏู", "ูู ูพุงุจู ุฏุงุฑู", "ูู ูพุงู ุจุฑุงุฏุฑุงู ุฏุงุฑู\nุงุณุชูุงุฏู ุดุฏ", "ูุฑุฏุงุธูุฑ ูุงูุงุฑ ูู ูพุงู\n#ุงูุฏุง", "ูุงูุงุฑ ุณูู ูู(ูพุงู)  ูพุฑุฏุณ ูุฑฺฉุฒ ุฏุงุฑู", "ูู ูพุงู ุฏุงุฑู", "ูู ูพุงู ุณูุฎุงุฑ ุฏุงุฑู\nุงุณุชูุงุฏู ุดุฏ", "ูู ูพุงู ุฏุงุฑู\n#ุงูุฏุง\nุงุณุชูุงุฏู ุดุฏ", "ูู ูพุงู ูุงฺฉุงุฑูู ุฏุงุฑู", "ูู ูพุงู ูุงูุงุฑ ุฏุงุฑู", "ูพุงู ุฏุงุฑู \nุงุณุชูุงุฏู ุดุฏ", "ูพุงู ุฏูุชุง ฺฉุฏ ุฏุงุฑู", "ูู ูพุงู ููู ุฏุงุฑู\nุงุณุชูุงุฏู ุดุฏ", "ูู ูพุงู ฺฉุฏ ุฏุงุฑู.", "ูู ูพุงู ุฏุงุฑู.\nุงุณุชูุงุฏู ุดุฏ", "ูู ูพุงู ุฏุงุฑู ูู ฺฉุฏ ููุชููู ุจูุฑุณุชู\nุงฺฏู ฺฉุณ ุจุง ุดูุงุฑู ุฏุงูุดุฌู ูุชููู ุจฺฏุฑู ุจุงุฏ", "ุณูู ูพุงู ๐ฅบ๐ฅ", "ุณูุงูุ ุณูู ูู ฑถ ุขุฐุฑ ุฏุงุฑู ฺฉุณ ุงฺฏู ุฎูุงุณุช ุงุทูุงุน ุจุฏู.", "ูู ูพุงู ุฏุงุฑู\n(ุฏููู)\nุงุณุชูุงุฏู ุดุฏ", "ูู ูพุงู ฺฉุฏ ุฏุงุฑู ฺฉุณ ููุฎูุงุฏุ", "ูุงูุงุฑ ูู ูพุงู\nุงุณุชูุงุฏู ุดุฏ", "ูู ูพุงู ฺฉููุชู\nุงุณุชูุงุฏู ุดุฏ", "ูู ูพุงู ูุฑุบ ุฏุงุฑู ุงฺฉุฑ ฺฉุณ ูุฎูุงุณุช ูุทูุง ูพุงู ุจุฏู", "ูุฑุฏุง ูู ูพุงู ุฏุงุฑู\n#ุงูุฏุง\n\n\nุงุณุชูุงุฏู ุดุฏ", "ฺฉุจุงุจ ูู ูพุงู ุฏุงุฑู"], "ุนููู": ["ุณูู ุนููู ฺูู ฺฉุจุงุจ ุฏุงุฑู\n\nุงูุฏุง ุดุฏ", "ุนููู ุฏุงุฑู\nููุท ูุฑฺฉ ุฏุงุฎู ุณููู ูพุงู ุจุฏู ฺูู ุชุงูุฑ ุฏุงุฑู ุจุงุฑฺฉุฏ ุฏูุจุงุฑู ููุชููู ุจูุฑุณุชู", "ุนููู (ุขุจฺฏูุดุช) ุฏุงุฑู\nุงุณุชูุงุฏู ุดุฏ", "ุณูู ุนููู ุฏุงุฑู ูุฑุฏุง", "ุณู ุดูุจู ุนููู ุฏุงุฑู", "#ุงูุฏุง\nฺูุงุฑุดูุจู\nฺฉูุจุฏู\nุนููู\nุงูุฏุง ุดุฏ.", "ุนููู ุฏุงุฑู \n#ุงูุฏุง", "ฺฉุฏ ุนููู\nุงุณุชูุงุฏู ุดุฏ", "ูุงูุงุฑ ุนููู ุงูุฑูุฒ", "ุณูู ูพุฑุฏุณ ุนููู ุฏุงุฑู", "ุณูู ูพุฑุฏุณ ุนููู ฺฉุฏ ูุงูุงุฑ ุฏุงุฑู", "ุนููู ุฏุงุฑู"], "ููุฑ": ["#ุณูู_ููุฑ ฺฉุฏ ุฏุงุฑู ุงูุฑูุฒ", "#ุณูู_ููุฑ ุฏุงุฑู", "ูุงุณู ูุฑุฏุง ฺฉุฏ ุณูู ููุฑ ุฏุงุฑู", "ุณูู ููุฑ ุฏูุชุง ุฏุงุฑู", "ุณูุงู ุจฺู ูุง\nูู ฺฉุฏ ูุฑุงููุด ุฏุงุฑู ฺฉุณ ูุฎูุงุฏ\nูุงู ุณูู ููุฑ!", "ุณูุงู\nุณูู ููุฑ ุฏุงุฑู.", "ูุฑุฏุง ูุงูุงุฑ ุณูู ููุฑ ุฏุงุฑู ู ุจุง ฺฉู ุนูุถ ูโฺฉูู", "ุณูุงู ุฏูุณุชุงู\nุณูู ููุฑ ฺฉุฏ ุฏุงุฑู ูุฑ ฺฉุณ ุงูุงู ุงููุฌุง ูุณุช ุจูุฑุณุชู ุจุฑุงุด ฺูู ูููุถ ูุดู ุชุง ฺูุฏ ุฏููู ุฏฺฏู", "ฺฉุฏ ุณูู ููุฑ ุจุฑุง ูุฑุฏุง ุฏุงุฑู", "ุฏูุชุง ฺฉุฏ ุณูู ููุฑ ุฏุงุฑู ุงูุฏุง ุฏุงุฏู ุดุฏ\nฺฉุฏ ฺฉู ูู ุงฺฏุฑ ุจูุฏ ุจฺฏุฏ ุจ ุฒุญูุช", "ุณูู ููุฑ ุ ฺฉุฏ ุฏุงุฑู. ุงฺฏุฑ ฺฉุณ ููู ุงูุงู ุณูู ูุณุช ุจฺฏู ฺฉุฏ ุจูุฑุณุชู.\nุงุณุชูุงุฏู ุดุฏ"], "ููุฑ": ["ููุฑูุง ฺฉุฏ ุฏุงุฑู", "ุณูู ููุฑูุง ูุงูุงุฑ ุฏุงุฑู", "ฒ ุชุง ฺฉูุจุฏู ุฏุงุฑู ููุฑ ูุง", "ฺฉุฏ ุฏุงุฑู ููุฑูุง", "#ุงูุฏุง ุณูู ููุฑ ูุง ุฒุจุง", "ูุฑุฏุง ููุฑูุง ุฒุจุง", "ุณูุงู \nฺฉุฏ ุฏุงุฑู ูุงุณู ููุฑูุง ุฒุจุง", "ููุฑ ฺฉุฏ ุฏุงุฑู", "ููุฑูุง ุฏุงุฑู ...\nุงุณุชูุงุฏู ุดุฏ", "ุณูู ููุฑูุง ุฒุจุง ุฏุงุฑู #ุงูุฏุง"], "ุฒุจุงู": ["ุฏุงูุดฺฉุฏู ุฒุจุงู ุฎุงุฑุฌ ุฏุงุฑู", "ุณูุงู ุจฺู ูุง \nูู ูุงูุงุฑ ุจุฑุง   ุฏูุดูุจู ู ุณู ุดูุจู ุฏุงูุดฺฉุฏู ุฒุจุงู ฺฉุฏ ุฏุงุฑู", "ุจฺู ูุง ุจุฑุง ูุฑุฏุง ูุงูุงุฑ ุฏุงูุดฺฉุฏู ุฒุจุงู ุฏุงุฑู\nฺฉุณ ูุฎูุงุฏุ"], "ุฑูุงูุดูุงุณ": ["ุณูุงู ูุงูุงุฑ ุฑูุงู ุดูุงุณ ฺฉุฏ ุฏุงุฑู\nูพุฑุฏุณ ูุฑฺฉุฒ ูุณุช"], "ุงุฌุชูุงุน": ["ุณูุงู ูุงูุงุฑ ุณูู ุนููู ุงุฌุชูุงุน ุฏุงุฑู", "ุณูู ุนููู ุงุฌุชูุงุน ฺฉุฏ ุฏุงุฑู.", "ุฏุงูุดฺฉุฏู ุนููู ุงุฌุชูุงุน ุฏุงุฑู", "ุฏุงูุดฺฉุฏู ุนููู ุงุฌุชูุงุน ูุงูุงุฑ ุฏุงุฑู"], "ูุฏุฑุช": ["ฺฉุฏ ุจุฑุง ุณูู ูุฏุฑุช ุฏุงุฑู", "ุณูู ูุฏูุฑูุช ุฏุงุฑู"], "ุงุณุชูุงุฏู": ["ูู.\nุงุณุชูุงุฏู", "ุงุณุชูุงุฏู ูฺฉูู โค๏ธ", "ุงุณุชูุงุฏู๐น", "man", "ุงุณุชูุงุฏูโค", "ุงุณุชูุงุฏ", "ูู ุงูฺฉุงู ุฏุงุฑู ูู ูุฎูุงู", "estefade", "ูู", "ู ุฎูุงู"], "ุงููุงุช": [], "ุนููู ู ูููู": ["ฺฉุฏ ุนููู ูููู ุฏุงุฑู"], "ูุฒฺฉ": ["ูุฑุฏุง ูุงูุงุฑ ฺฉุณ ูุฎูุงุฏุุฏุงูุดฺฉุฏู ุชุฑุจุช ุจุฏู", "ฺฉุฏ ูุทุงูุนุงุช ุฌูุงู ุฏุงุฑู. ุจฺู ูุง ุฒุจุงููุง ูู ูุชููู ุจฺฏุฑู.", "ุฒุฑุดฺฉ ูพูู ุจุง ูุฑุบ ุณูู ูุฒฺฉ\n#ุงูุฏุง", "ุณูู ูุฒฺฉ ุชู ูุงู\n#ุงูุฏุง\nูุงฺฏุฐุงุฑ ุดุฏ", "ฺฉูุจุฏู ุชุฑุจุช ุจุฏู"], "ูุชูุฑูู": ["ุขูุง ุณูุช ุงูุฑุขุจุงุฏุ", "ุดุงู ุงูุดุจ ฺูุ", "ูู ูพุงู ูฺฏู ฑฒ:ณฐ ุจู ุจุนุฏ ุจุง ฺฉุฏ ูุฏู", "ุจฺู ูุง ุงู ฺฉุฏุง ุชุง ฺู ุฏูู ูุดู ุงุฒุด ุงุณุชูุงุฏู ฺฉุฑุฏุ", "ุจุง ุฏุงุฏุง", "ูุทูุง ูพุงู ุจุฏุฏ", "ุดฺฉุฑ๐", "ุงูุชุญุงู ูฺฉุฑุฏู ูู ฺฏูุง ูุดู", "ูพุดุช ุจุงุดฺฏุงู ุฏุงูุดุฌู", "ุจุง ูุงุฑ ูุงฺฉุณุ", "ุงฺฏู ุจุง ฺฉุฑูู ุฒุฏ ุจุฑูฺฏุฑุฏู \nุจุง ูุงุฑูุงฺฉุณ ุจุฒู", "ุจุงุฑ ูฺฏุฑู ุฌุฑูู ูุดูุ", "ูุฏุฑุช ฺฉุณ ูุฏุงุฑู ุ", "ูู ูพุงู ูุฏุงุฑูุ", "ุจฺู ูุง ุฏุฑุฎูุงุณุช ูุฏู ๐\nุงุณุฑ ุดุฏู ุฎุฏุง", "ููุฑ ุณูู ููุฑ ูุดูุ", "ฑตุชููู\nูพูุฌุดูุจู ฺฉู ููุชู ุจุนุฏ ุฑู ุฑุฒุฑู ูฺฉู\nูู ูฺฉโฺฉูู ุชูุฒุนุด ุฌูุนู ูุณ", "ฺู ุฏููุง ุงุณุชูุงุฏู ูโฺฉูุ", "ูุงูุงุฑ  ู ุดุงู ุฎูุงุจฺฏุงู ูุงุทูู ุฏุงุฑู\n\nูุงูุงุฑ ุงุณุชูุงุฏู ุดุฏ", "ุจุง ูุงุฑูุงฺฉุณ ุจุฑู", "ุนูุถ ูฺฉู ุงุฑู ุจุณุฌู", "ุฎูุงุจฺฏุงู ูุงุทูู ฺฉุฏ ุฏุงุฑู\nุงุณุชูุงุฏู", "ูู ุจุงูุง ุฎุฑุฏุงุฑู", "ูุงูุงุฑ ุชุง ฺูุฏู", "ููุฑูุง ฺฉุฏ ูุฎูุงู", "ููุฑ ุงูู ุตู ุณุงุนุช ฺูุฏ ูพุงู ฺฏุฐุงุดุชูุ๐ค๐", "ูฺฏู ุชุง ููุช ูุงูุงุฑ ุญู ูุดู", "ุงุชููุงุจ", "ุบูุจ ุ๐ค\nุงฺฏุฑ ูุณุช ุฌูุงุจ ุจุฏู ๐ค", "ุจฺู ูุง ุงูู ฺฉ ูฺฏู ุจุฏูู ุฑุฒุฑู ุณุงุนุช ฑููู ุจุง ููุชุด ฺูุฏูุ", "ุจุง ูุงุฑ ูุงฺฉุณู", "ฺฉุฏูู ุจุงูุงุนู ฺฉุฏูู ูพุงูุ๐", "ูุจูุด ฺฉ ุฎู ุงุจุชุฏุง ุจูุฏ ุงูุงู ุจุงุฒ ฺฉู ุจูุชุฑ ุดุฏู", "๐น๐น๐๐ป", "ุดุงู ฺูุฑุงู", "ุณูู ููุฑ  ูุฎูุงู", "ุฎูู ุดุฏ ูุญุชุฑูุงูู", "ุนุฑุถู ู ุชูุงุถุง ูู ุจุงูุง ุงุตูุง ุจุง ูู ููุฎูู ูุฏุงุฑู๐", "ูุดู ฺฉ ุฑุงูููุง ฺฉูู", "ูุตุฑู ุดุฏ", "ูุนูููุง ููู  ุบุฐุง ุชููู ูุดู ุชุง ุงูู ูููุน \nูู ููโุฏู", "ฺฏุฑูุชู", "ุงุฒ ุณูู ููุฑ ฺฉู ฺฉูุงุฑ ุฏุฑูุงูฺฏุงูู ูุดูุ", "ุจูู ูพู", "#ุฏุฑุฎูุงุณุช \nูู ูพุงู", "ูฺฏุฑู", "ู ุณูู ููุฑ ูุฑู ูฺฉูู ุจุง ูู ูพุงู. ุฏููุง ุจุบู ฺฉููฺฉ ุฑู ุจุงุฏ ุจุฑ ุฏุงุฎู(ุจุฑูู ุฏุงูุดฺฏุงู)", "ู ุณูุงู\nุงูููุช ุงูุฌุงุณุช ุจฺฏู ( ุงุณุชูุงุฏู )\nุง ูพ ูุ\nูุฑููุช ุงููู ููุฑ ุฑูพูุง ูฺฉูู ุชู ฺฏุฑูู ุชู ูพุฑุงูุช ูฺฏู ูุจู ุชู ฺฏุฑูุชู ๐๐๐", "ฺ ูฺฏ ๐จ", "ุดุงู ฺูุฑุงู ูุจูุฏ ๐ุ", "ฺุฑุง ูพุงฺฉ ูฺฉูุ๐", "ทฑฺฉุฏุฏุงุฑู", "ูุงูุงุฑ ู ุดุงู ุฎูุงุจฺฏุงู ูุงุทูู ุฏุงุฑู", "ุฎุฑ ุดุงู ููุท ุชู ุฎูุงุจฺฏุงูู", "ุชุดฺฉุฑ ุงุฒ ุฏุบุฏุบู ุดูุง๐", "ูุนุงุจ ูพูฺฏ ุจุงูุง", "ุจู ุงู ุบุฐุง ูุฏุฏ ุจุณุฌู", "ฺูุ", "ุณุงุนุช ุงุฒุฏู ู ููโ ุฏูุงุฒุฏู ุจูู ูพุงู ุจุฏู", "ุชู ูุงุฑูุงฺฉุณ ุดุฏ ูู ุฒุฏู", "ุฏูุณุชุงู ุตุจุญุงูู ุจุฑุง ููุชู ุจุนุฏ ฺุทูุฑ ุจุงุฏ ุฑุฒุฑู ฺฉููุ", "ฺุฑุง ูุฎููุฏ", "ฺุฌูุฑ ูฺฏู ูู ูพุงู ูฺฏ ุงุณุชูุงุฏู\nูฺฏู ูู ุจุงูุง ูฺฏ ุงุณุชูุงุฏู ู ููุฒูุงู ูู ูพุงู ูู ุจุงูุง\nุฎูุงูุดุง ุงุฌุงุฒู ุจุฏู ุงูู ฺฉ ูุชููุณู ุบุฐุง ุฑุฒุฑู ฺฉูู ุจฺฏุฑู \nุงูุจุชู ฺฉ ููุด ุฌููุช๐งโ๐ฆฏ๐งโ๐ฆฏ", "ููุท ูููุฏ ุจฺู ูุง\nุขุจฺฏูุดุชู ุญุดุด ูุฏู ุฏุงูุดฺฏุงู๐", "ูุฎุฑู", "ุณูุงู \nฺฉุณ ูู ูพุงู ฺฉุฏ ุฏุงุฑูุ", "ููู ูุณุช\nฺูุฏ ุจุงุฑ ุชูุงุด ฺฉู ุจูุฎุฑู ุงูฺฉ ูุดู\nูุงุณู ูู ูุนูููุง ุจุงุฑ ุณูู ุดุงุฑฺ ูุดู\nุงููุง ูู ฺฉู ุดุงุฑฺ ูุดุฏู ุจุฑูฺฏุฑุฏู ุจุนุฏ ฺูุฏ ุณุงุนุช", "ุง ุนู", "Firefox ุจุฑู", "ูุงูุงุฑ ูุงุทูู ุณู ุดูุจู ุฏุงุฑู", "ฺฉุฏ ููุฑูุง ุฏุฑุฎูุงุณุช :))", "ุณูุงู.\nุจุจุฎุดุฏ ุณูุงู ุชฺฉุฑุงุฑู\nุงูุง ุจุฑุง ุซุจุช ูุดุฏู ุงูุฒุงุด ุงุนุชุจุงุฑ ฺู ุจุงุฏ ฺฉุฑุฏ ุ", "๐คฆโโ๐คฆโโ๐", "ฺฺฉุงุงุฑ ฺฉูููุุุ", "ุงฺฏุฑ ฺฉุฏ ูพุฏุง ฺฉุฑุฏ ุจู ููู ุจฺฏู :)", "ูฺฏู ูุฑ ุฏูุนู ฺฉู ูฺฏุฑู ุจุงุจุชุด ุฌุฑูู ููฺฉููุ๐ค๐ค", "ุจุฑูฺฏุฑุฏู ุจู ุญุณุงุจุช\nุจุง ูุงุฑูุงฺฉุณ ุจุฒู ุงูฺฉ ูุดู", "๐ุฌูุนู ุจุงูฺฉ ูุง ูู ุชุนุทูู\nุนุงู", "ุฎูุงูุด ูฺฉูู๐น", "ุณูุงู ฺฉู ฺฉุณ ูุฎูุงุฏุ", "ุจุงุฏ ูุงุณ ุชุง ุขุฎุฑ ููุชุุฑูุฒ ูุฑูุด ุจฺฏุฑ.", "ุจฺู ูุง ุณุฑุน \nุจุงฺฏ ูุงุฑู ุดูุงุณุง ูฺฉูู ๐ฅ๐", "ุฏุฑุฎูุงุณุช ูู ุจุงูุง", "ูู ูพุงู ฺฉุณ ุบุฐุง ุฏุงุฑู", "ุฏุฑุฎูุงุณุช ูุฏุงุฑู", "ูฺฉุฑ ููฺฉูู.ุจุงุฏ ูุฑููุชู ุจุงุดู ุงุญุชูุงูุง.", "ุจุง ูุช ุซุงุจุช ูุดฺฉู ูุฏุงุฑู ุงูุขู ุชุณุช ฺฉุฑุฏู", "ุณูุง ูุณุช ุงุตู๐", "ุฎุจ ุจุฑู ุชู ุณุงูุงูู ุฎูุฏุด ุจูุช ูุดูู ูุฏู ฺฉุฏูู ูุนุฏู ุฑู ูุชูู ุจฺฏุฑ", "ุจุจู ุงูุฒุงูุง ุฑุจุท ุจู ูฺฏุฑูุชู ุบุฐุง ูุฏุงุฑู. ุงฺฏู ุฑุฒุฑู ฺฉู ู ูฺฏุฑ ุฌุฑูู ูุด. ูู ุงูฺฉู ูููุฌูุฑ ุจุฎูุง ูฺฏุฑ ู ุฑุฒุฑู ูฺฉุฑุฏู ุจุงุด", "ุจุฑุง ููู ููุด ุงูุฌูุฑ ูุดู ุณุฑฺโฺฉู ุชุบุฐู ุฏุงูุดฺฏุงู ุชูุฑุงู ุฏููู ุณุงุช ุฑู ุจุฑู ูู ุงูู ุฑู", "ุฏุฑ ฺฏูุชุฏ\nุจฺู ูุง ุฎูุงุณุชู ูพ ู๐๐ผ", "๐๐", "ุชุฑู ูุจู ูู ุจูุฏ ูู ุฎู ููุชุง ูุดุฏ ุจฺฏุฑู ูู ุฌุฑูู ุง ูฺฏุฑูุชู", "ฑฑ:ณฐ ููุธูุฑุชูุ", "ุจุฑุงุชูู ููุฑุณุชู", "ุนุฒุฒู ุงุณุชูุงุฏู ุดุฏ", "ุญุฏูุฏ ฒ", "ุจุจุฎุดุฏ ุดุฑููุฏู \nููุฏููุณุชู", "ุงูุฏุง ุดุฏ", "ุจุงุฒู ูู", "ุณุฏ", "ูู ุจุงูุง ฺฉุณ ฺฉุฏ ุฏุงุฑูุ", "ุดุงู ฺูุฑุงู ฺฉุณ ูุฎูุงุฏุ", "ูู ูููุฒ ูุฑุตุช ุฏุงุฑู", "ููุธูุฑ ูููู ุจุงุฑฺฉุฏ ุฏุฑ ูุณูุช ูุฑุงููุด ฺฉุงุฑุช ูุณุช", "ุญุณุงุจ ู ฺฉูู ู ุจูู ุชุงฺฉุณ ุณูุงุฑ ุดู ุงุฒ ูุฏูู ุงูููุงุจ ุจุฑู ุงูุฑุขุจุงุฏ ุงุฑุฒููุชุฑ ุงุฒ ุบุฐุง ุจุฑูู ูุดูู ููุฐุง ุงุณุชูุงุฏู", "ูู ฺฉุฏ ุฏุงุฑู", "ูู ูุดฺฉู ูุณุช", "๐๐", "ุง ุฎุฏุง\nูพูู ุชุฑฺฉุฏ๐๐", "ุฏุฑุฎูุงุณุชู ุจุงูุง", "ุณูู ููุฑ ฺฉุฌุงุณ ุ", "ุงุณุชูุงุฏู = ุชุนูุถ", "ฺฉู ูพุณุฑุงู ุฏุงุฑูุ", "ุจุฎุฏุง ุงููู ุฎุฑุฏู ุฑูุชู ุฑุฎุชู ุงุดุบุงู ุณุณุด ุชุฑุด ูุณููู ุดุฏู ุจู ูู ูุฏุงุฏ", "ฺุดู ูพูุฒุด๐๐", "ฺูุฏ ุจุงุฑ ุงูุชุญุงู ฺฉุฑุฏู ูุดุฏ ูู ุจุนุฏ ู ูุฏุช ุฏุฑุณุช ุดุฏ.", "ูุงูุงุฑ ูุงุทูู ุฏุงุฑู", "ุณูุงู ุจฺูโูุง ูู ุฏุดุจ ุงูุฒุงุด ุงุนุชุจุงุฑ ุฒุฏู ูู ุจุนุฏ ุงุฒ ูพุฑุฏุงุฎุช ูพูู ุงูุฒุงุด ูุฎูุฑุฏ ู ููุฏููู ูุจูุบ ฺฉู ุฒุฏู ุงูุงู ุจุฑฺฏุดุช ุฎูุฑุฏู ุง ูู ููุฏููุฏ ฺู ุทูุฑ ูุดู ุงูู ฺฺฉ ฺฉุฑุฏุ", "ุฌุฑูู ุด ฺุฌูุฑูุ", "ูู ุฏุฑูุฒู ูุฎูุงุณุชู ุจุฑุง ุดูุจู ุจฺฏุฑู ูฺฏุฑูุช.", "๐๐บ", "ฺฉุฏ ูู ุจุงูุง ฺฉุณ ุฏุงุฑูุ", "ุฑุฒุฑู ุบุฐุง ุงุฏุชูู ูุฑู\n\nhttp://dining2.ut.ac.ir", "ูููููู ุงุฒ ูพุงุณุฎ ุดูุง", "ูู ุฏุฑูุฒู ูุชููุณุชู. ุชููุนุงุช ุฏุงุฑ", "โ๐ป", "ุณูุงู ฺ ุฑูุฒุ", "ุณูุงูุ ูู ุจุงูุง  ุฏุฑุฎูุงุณุช.", "ุถุง ุฏุงุฑู ูุฎูุงุ", "๐๐", "ุชุง ฺฉ ู ูู ูุฏู", "ุชุง ฺฉ ุณุงุนุช ูุฏู.", "ููู ูุชููุณุชู", "ูู ูพุงู ุงุณุชูุงุฏู ูฺฉูู", "ุตุจุญุงูู ฺุฑุง ููุฏูุ", "ูู ููู ุงูุฑูุฒ ุฏู ุจุงุฑ ุชู ุณูู ุงูุชุญุงู ฺฉุฑุฏู ููุท ุชุง ูพูุฌ ุฏููู ูุฏุงุฏ", "ุณูู ุงุตู ฺฉู ุชุง ูุดุช ู ููู ูฺฉ ฺฉูู \nุณุงุฎุชููู 6 ุชุง ูุดุช", "ุจุง ูพู", "๐ปุฌุฑูู ูุฎูุฑุฏู ุบุฐุง ุฑุฒุฑู ุดุฏู ุฏุฑ ุณุงูุงูู ุชุบุฐู\n\n๐นุจู ููุธูุฑ ุฌููฺฏุฑ ุงุฒ ุงุณุฑุงู ู ุญูุธ ุญููู ุฏุงูุดุฌูุงูุ ุงุฒ ฑด ูุฑูุฑุฏู ูุงู ฑดฐฑ ุฏุฑ ุตูุฑุช ุฑุฒุฑู ุบุฐุง ู ุนุฏู ุฏุฑุงูุช ุขู ุชุง ด ูุฑุชุจู (ุงุนู ุงุฒ ูุนุฏู ูุงูุงุฑ ุง ุดุงู) ุฏุฑ ูุฑ ูุงู ุจุฑุง ุฏุงูุดุฌูุงู ุฎูุงุจฺฏุงู ู ุชุง ฒ ูุฑุชุจู (ูุนุฏู ูุงูุงุฑ) ุจุฑุง ุฏุงูุดุฌูุงู ุบุฑ ุฎูุงุจฺฏุงูุ ูุนุงุฏู ฒ ุจุฑุงุจุฑ ููุช ูุนุฏู ุบุฐุง ุจู ุงุฒุง ูุฑ ูุนุฏู ุจู ุตูุฑุช ุฎูุฏฺฉุงุฑุ ุชูุณุท ุณุงูุงูู ุชุบุฐู ุงุฒ ฺฉู ูพูู ุฏุงูุดุฌู ฺฉุณุฑ ุฎูุงูุฏ ุดุฏ.\n\n๐นูพุณ ุงุฒ ุขู (ุนู ุงฺฏุฑ ุจุด ุงุฒ ด ูุนุฏู ุบุฐุง ุชูุณุท ุฏุงูุดุฌู ุฎูุงุจฺฏุงู ู ุง ุจุด ุงุฒ ฒ ูุนุฏู ุบุฐุง ุชูุณุท ุฏุงูุดุฌู ุบุฑ ุฎูุงุจฺฏุงู ุฏุฑุงูุช ูุดูุฏ) ุจุฑุงุจุฑ ุจุง ููุช ุชูุงู ุดุฏู ุบุฐุง (ณถฐฐฐฐ ุฑุงู)(ููุช ุจุฑูุฒุฑุณุงู ุฎูุงูุฏ ุดุฏ) ุจู ุงุฒุง ูุฑ ูุนุฏู ุบุฐุง ุงุฒ ุงุนุชุจุงุฑ ฺฉู ูพูู ุฏุงูุดุฌู ุฏุฑ ุณุงูุงูู ุชุบุฐู ฺฉุณุฑ ุง ุฏุฑ ุตูุฑุช ุนุฏู ููุฌูุฏ ฺฉุงูุ ุจุฏูฺฉุงุฑ ุฎูุงููุฏ ุดุฏ.\n\n๐นูุฐุง ุงฺฉุฏุงู ุชูุตู ู ฺฏุฑุฏุฏ ุญุชูุงู ุฏุฑ ุตูุฑุช ุงุทููุงู ุงุฒ ุฏุฑุงูุช ุบุฐุง ูุณุจุช ุจู ุฑุฒุฑู ุขู ูุนุฏู ุงูุฏุงู ููุงุฏ ู ุฏุฑ ุบุฑ ุงู ุตูุฑุชุ ุบุฐุง ุฑุฒุฑู ุดุฏู ุฎูุฏ ุฑุง ทฒ ุณุงุนุช ูุจูุ ุงุฒ ุณุงูุงูู ุญุฐู ูุฑูุงุฏ.", "ฺฉุดู ุจุฏู ูุง ุฎุจ", "ุฎุฑ", "ฺฉู ุฏุงุฑู.", "ูุฑุณ๐", "ุจุง ูููู ููุช ุณุงูุงูู ุญุณุงุจ ูฺฉููุุุ", "ุณูุฎุช", "โ", "ุดุงู ฺูุฑุงู ุฏุงุฑู", "ูุฑุฏุง ูุจู ุงุฒ ุธูุฑ", "ูู ุธูุฑ ุฏุงุฏู\nุจุง ฺฉุฑูู  ู ุฏุฑฺฏุงู ููุช", "ุฎูุงุจฺฏุงู ฺฉู ุฏุงุฑู", "ูพ", "ูู ูพุงู #ุฏุฑุฎูุงุณุช\nูพู", "ููู ูููู", "ุขูุงู. ุงููู ููุฏููู ุฑุงุณุชุด", "๐๐๐๐", "ุงุฑู", "ุขุฑู", "ุจุง ฺฉู ุชุนูุถ ููฺฉููุ", "ฺู ููู ูุงูุงุฑ๐๐๐", "ุจุญุซู ุดฺฉูู", "ุณูุงู\nฺฉุณ ฺฉู ุดุงู ุฏุงุฑูุ", "ุจุงุฑ ุจุง ูพ ุณ ุชุณุช ฺฉู", "ุขุฑู ููู ููโุชููู.", "ุขุฎู ฺฉุดูุจู ุฑู ูู ุงุฒ ุตุจุญ ููุงูุฑุฏ ุงูู ฺฉู ูููุฒ ููุช ุฏุงุดุช", "๐๐๐๐๐๐", "ุฏูุณุชุงู ุชูุงู ุดุฏ"], "ุชุนูุถ": ["#ุชุนูุถ ูู ุจุงูุง ุจุง ฺฉู ูพุณุฑุงู\nุงุณุชูุงุฏู ุดุฏ.", "ูู ุจุงูุง  ุชุนูุถ ุจุง ูพุงู", "ูู ุจุงูุง ุฏุงุฑูุ ฺฉู ูุฎูุงู", "ุชุนูุถ ููุจ ุจุงูุง ุจุง  ูู ูพุงู", "ุชุนูุถ\nูู ุจุงูุง ุฏุงุฑู ุจุง ูพุงู", "ูู ุจุงูุง ุฏุงุฑู\nุจุง ูพุงู ุนูุถ ูฺฉูู", "ูู ูพุงู ุฏุงุฑู ุจุง ุจุงูุง ุนูุถ ูฺฉูู(ูุงฺฉุงุฑุงู)", "ุณูู ูู ุจุงูุง ุฏุงุฑู ุจุง ูพุงู ุง ููุฑ ุชุนูุถ ูฺฉูู", "ููุฑ\nูุนุงูุถู ุจุง ฺฉู", "ฺฉุณ ูุณุช ฺูุงุฑุดูุจู ูุง ุจุฎูุงุฏ ุชุนูุถ ฺฉูู ุจุง ูู (ุฏุงูุดฺฉุฏู ุนููู ุงุฌุชูุงุน ุฑู ุจุง ุฑูุงู ุดูุงุณ )", "ูู ุจุงูุง ุฏุงุฑู\nุจุง ฺฉู ุฏุงูุดฺฏุงู ฺฉุณ ุนูุถ ููฺฉููุ", "ูพุงู ุฏุงุฑู ุจุง ุจุงูุง ุนูุถ ูฺฉูู", "ูู ูพุงู ุฏุงุฑู ุจุง ฺฉู ุนูุถ ูฺฉูู", "ุชุนูุถ \nูู ูพุงู ุฏุงุฑู \nูู ุจุงูุง ูุฎูุงู", "ูู ุจุงูุง ูุฑุบ ุฏุงุฑู ุจุง ฺฉู ุชุนูุถ ูฺฉูู", "ฺฉู ูพุณุฑุงู ุฏุงุฑู ุชุนูุถ ุจุง ูู ูพุงู", "ูุงูุงุฑ ูู ฑถ ุขุฐุฑ ุฏุงุฑู ุจุง ุฎูุงุจฺฏุงู ุนูุถ ูฺฉูู.", "ุณูู ูู ูพุงู ุฌุงุจุฌุง ุจุง ููุฑ", "ูู ูพุงู ุชุนูุถ ุจุง ุณูู ููุฑ", "ุณูุงู ุฏูุณุชุงูุ\nูุฑุฏุง ูุงูุงุฑ ูู ูพุงู ุฏุงุฑู.\nฺฉุณ ูุณุช ุณูู ฺฉู ุฏุงุดุชู ุจุงุดู ู ุจุฎูุงุฏ ุนูุถ ฺฉููุ", "ุณูุงู\nูู ุจุงูุง ุฏุงุฑู ุจุง ูพุงู ุชุนูุถ ู ฺฉูู", "ูู ุจุงูุง ุฏุงุฑู ุจุง ฺฉู ูพุณุฑุงู ุชุนูุถ ู ฺฉูู", "ูู ูพุงู ุฏุงุฑู ูู ุจุงูุง", "ูู ูพุงู ุฏุงุฑู\nูู ุจุงูุง ูุฎูุงู", "ุธุชุนูุถ ูู ุจุงูุง ุจุง ูพุงู (ุจุงูุง ุฏุงุฑู)", "ูู ูพุงู ุฏุงุฑู \nุจุง ูู ุจุงูุง ุชุนูุถ ูฺฉูู", "ูู ูพุงู ุฏุงุฑูุ ุจุงูุง ูุฎูุงู", "ูู ุจุงูุง (ุฌูุฌู) ุฏุงุฑู ูู ูพุงู (ุฌูุฌู) ูุฎูุงู\nุงุณุชูุงุฏู ุดุฏ", "ุชุนูุถ\n ูู ุจุงูุง ุฏุงุฑู ูู ูพุงู ูุฎูุงู", "ูู ูพุงู ุฏุงุฑู ูุนุงูุถู ุจุง ูู ุจุงูุง"]}